cablyai/__init__.py
cablyai/audio.py
cablyai/chat.py
cablyai/client.py
cablyai/images.py
cablyai/moderations.py
cablyai-0.0.5.dist-info/LICENSE
cablyai-0.0.5.dist-info/METADATA
cablyai-0.0.5.dist-info/WHEEL
cablyai-0.0.5.dist-info/RECORD
