Metadata-Version: 2.1
Name: cablyai
Version: 0.0.5
Summary: A library meant to be a wrapper for the CablyAI service.
Author: acattoXD
Author-email: acatto@acatto.lol
Requires-Python: >=3.10,<4.0
Classifier: Programming Language :: Python :: 3
Classifier: Programming Language :: Python :: 3.10
Classifier: Programming Language :: Python :: 3.11
Classifier: Programming Language :: Python :: 3.12
Classifier: Programming Language :: Python :: 3.13
Requires-Dist: aiohttp
Requires-Dist: beautifulsoup4
Requires-Dist: googlesearch-python
Requires-Dist: requests
